yahoo_finance_mcp/__init__.py
yahoo_finance_mcp/server.py
yahoo_finance_mcp-0.1.2.dist-info/licenses/LICENSE
yahoo_finance_mcp-0.1.2.dist-info/METADATA
yahoo_finance_mcp-0.1.2.dist-info/WHEEL
yahoo_finance_mcp-0.1.2.dist-info/entry_points.txt
yahoo_finance_mcp-0.1.2.dist-info/top_level.txt
yahoo_finance_mcp-0.1.2.dist-info/RECORD
